{
  "rate-limit": {
    "name": "Rate Limiter",
    "description": "IP-based rate limiting middleware with pluggable storage strategies",
    "environments": {
      "express": {
        "core": "blocks/rate-limiter/express/base.ts.txt",
        "variants": {
          "memory": {
            "dependencies": [],
            "files": ["blocks/rate-limiter/express/store-memory.ts.txt"]
          },
          "redis": {
            "dependencies": ["ioredis"],
            "files": ["blocks/rate-limiter/express/store-redis.ts.txt"]
          }
        }
      }
    }
  },
  "error-handler": {
    "name": "Global Error Handler",
    "description": "Centralized Express error handling...",
    "environments": {
      "express": {
        "core": "blocks/error-handler/express/base.ts.txt",
        "variants": {
          "default": {
            "dependencies": ["zod"],
            "devDependencies": ["@types/express"],
            "files": [
              "blocks/error-handler/express/app-error.ts.txt",
              "blocks/error-handler/express/errors.ts.txt",
              "blocks/error-handler/express/http-status.ts.txt",
              "blocks/error-handler/express/throw-error.ts.txt",
              "blocks/error-handler/express/global-error-handler.ts.txt",
              "blocks/error-handler/express/async-handler.ts.txt",
              "blocks/error-handler/express/index.ts.txt"
            ]
          }
        }
      }
    }
  }
}
